{
  "timestamp": "2026-07-21T23:56:20.772Z",
  "time": "5:26:20 AM",
  "games": [
    {
      "name": "DESAWAR",
      "timing": "05:00 AM",
      "result": "05",
      "oldResult": "73",
      "newResult": "05",
      "timestamp": "2026-07-21T23:56:20.812Z"
    },
    {
      "name": "FARIDABAD",
      "timing": "06:00 PM",
      "result": "XX",
      "oldResult": "06",
      "newResult": "XX",
      "timestamp": "2026-07-21T23:56:20.817Z"
    },
    {
      "name": "GHAZIABAD",
      "timing": "09:25 PM",
      "result": "XX",
      "oldResult": "82",
      "newResult": "XX",
      "timestamp": "2026-07-21T23:56:20.818Z"
    },
    {
      "name": "GALI",
      "timing": "11:25 PM",
      "result": "XX",
      "oldResult": "11",
      "newResult": "XX",
      "timestamp": "2026-07-21T23:56:20.818Z"
    }
  ]
}
