{
  "timestamp": "2026-07-07T22:34:25.387Z",
  "time": "4:04:25 AM",
  "games": [
    {
      "name": "DESAWAR",
      "timing": "05:00 AM",
      "result": "XX",
      "oldResult": "19",
      "newResult": "XX",
      "timestamp": "2026-07-07T22:34:25.409Z"
    },
    {
      "name": "FARIDABAD",
      "timing": "06:00 PM",
      "result": "XX",
      "oldResult": "04",
      "newResult": "XX",
      "timestamp": "2026-07-07T22:34:25.415Z"
    },
    {
      "name": "GHAZIABAD",
      "timing": "09:25 PM",
      "result": "XX",
      "oldResult": "48",
      "newResult": "XX",
      "timestamp": "2026-07-07T22:34:25.417Z"
    },
    {
      "name": "GALI",
      "timing": "11:25 PM",
      "result": "XX",
      "oldResult": "41",
      "newResult": "XX",
      "timestamp": "2026-07-07T22:34:25.417Z"
    }
  ]
}
