{
  "timestamp": "2026-07-11T14:59:52.928Z",
  "time": "8:29:52 PM",
  "games": [
    {
      "name": "DESAWAR",
      "timing": "05:00 AM",
      "result": "53",
      "oldResult": "26",
      "newResult": "53",
      "timestamp": "2026-07-11T14:59:52.954Z"
    },
    {
      "name": "FARIDABAD",
      "timing": "06:00 PM",
      "result": "32",
      "oldResult": "74",
      "newResult": "32",
      "timestamp": "2026-07-11T14:59:52.956Z"
    },
    {
      "name": "GHAZIABAD",
      "timing": "09:25 PM",
      "result": "XX",
      "oldResult": "42",
      "newResult": "XX",
      "timestamp": "2026-07-11T14:59:52.953Z"
    },
    {
      "name": "GALI",
      "timing": "11:25 PM",
      "result": "XX",
      "oldResult": "35",
      "newResult": "XX",
      "timestamp": "2026-07-11T14:59:52.954Z"
    }
  ]
}
